{
	"name": "Go",
  "dockerComposeFile": "docker-compose.yml",
  "service": "app",
  "workspaceFolder": "/workspaces/${localWorkspaceFolderBasename}",
  "settings": { 
		"terminal.integrated.shell.linux": "/bin/zsh",
		"go.gopath": "/go",
		"go.useGoProxyToCheckForToolUpdates": false,
		"go.useLanguageServer": true
  },
  "extensions": [
		"golang.Go",
  ],
  "runArgs": [
    // security and capability needed for ptrace-based debugger for golang
    // https://code.visualstudio.com/docs/remote/create-dev-container#_set-up-a-folder-to-run-in-a-container
    "--cap-add=SYS_PTRACE", "--security-opt", "seccomp=unconfined",
  ],
  "forwardPorts": [8080],
  "postCreateCommand": "go version",
}